Metadata-Version: 2.1
Name: address-magic
Version: 0.1.1
Summary: address parsing
Home-page: UNKNOWN
Author: Nsaspy
License: MIT
Platform: UNKNOWN
License-File: LICENSE
